func_util/__init__.py
func_util/func_util.py
func_util/ordered_set.py
func_util/predicate.py
func_util-1.0.1.dist-info/AUTHORS.md
func_util-1.0.1.dist-info/LICENSE.txt
func_util-1.0.1.dist-info/METADATA
func_util-1.0.1.dist-info/WHEEL
func_util-1.0.1.dist-info/top_level.txt
func_util-1.0.1.dist-info/RECORD
