Metadata-Version: 2.1
Name: func_util
Version: 1.0.1
Summary: some extra utility functions under python
Author: AIACE
Project-URL: Homepage, https://git.aiacesz.com/aiacee/pycore-util
Keywords: util
Classifier: Development Status :: 3 - Alpha
Classifier: Intended Audience :: Developers
Classifier: Topic :: Software Development :: Build Tools
Classifier: Programming Language :: Python :: 3
Classifier: Programming Language :: Python :: 3.8
Classifier: Programming Language :: Python :: 3.9
Classifier: Programming Language :: Python :: 3.10
Classifier: Programming Language :: Python :: 3.11
Classifier: Programming Language :: Python :: 3.12
Classifier: Programming Language :: Python :: 3.13
Classifier: Programming Language :: Python :: 3 :: Only
Requires-Python: <4,>=3.8
License-File: LICENSE.txt
License-File: AUTHORS.md
Requires-Dist: toolz ==0.*
